{
  "gitSyncId": "69bdc9bc2381c634c51fcd0b_0f4d3dd4-a569-4f72-aaa3-48f60a367f47",
  "id": "Order Page New Version_updateOrderStatus",
  "pluginId": "restapi-plugin",
  "pluginType": "API",
  "unpublishedAction": {
    "actionConfiguration": {
      "autoGeneratedHeaders": [
        {
          "key": "content-type",
          "value": "application/json"
        }
      ],
      "body": "{\n  \"status\": \"{{ inpStatus.text }}\"\n}",
      "bodyFormData": [],
      "encodeParamsToggle": true,
      "formData": {
        "apiContentType": "application/json"
      },
      "headers": [],
      "httpMethod": "PUT",
      "httpVersion": "HTTP11",
      "paginationType": "NONE",
      "path": "/orders/{{ Table1.selectedRow.order_id }}/status",
      "pluginSpecifiedTemplates": [
        {
          "value": true
        }
      ],
      "queryParameters": [],
      "timeoutInMillisecond": 10000
    },
    "confirmBeforeExecute": false,
    "datasource": {
      "id": "Yushu CMS",
      "isAutoGenerated": false,
      "name": "Yushu CMS",
      "pluginId": "restapi-plugin"
    },
    "dynamicBindingPathList": [
      {
        "key": "path"
      },
      {
        "key": "body"
      }
    ],
    "name": "updateOrderStatus",
    "pageId": "Order Page New Version",
    "runBehaviour": "MANUAL",
    "userSetOnLoad": false
  }
}