{
  "gitSyncId": "69afa6c79e39756f62038403_eda8e388-2bbb-482c-84da-abb1fa9d774f",
  "unpublishedPage": {
    "isHidden": false,
    "layouts": [
      {
        "dsl": {
          "backgroundColor": "none",
          "bottomRow": 410,
          "canExtend": true,
          "containerStyle": "none",
          "detachFromLayout": true,
          "dynamicBindingPathList": [],
          "dynamicTriggerPathList": [],
          "leftColumn": 0,
          "minHeight": 1292,
          "parentColumnSpace": 1,
          "parentRowSpace": 1,
          "rightColumn": 4896,
          "snapColumns": 64,
          "snapRows": 124,
          "topRow": 0,
          "type": "CANVAS_WIDGET",
          "version": 94,
          "widgetId": "0",
          "widgetName": "MainContainer"
        }
      }
    ],
    "name": "Inventory",
    "slug": "inventory"
  }
}